setup.py
InverseProblem/__init__.py
InverseProblem/functions.py
InverseProblem.egg-info/PKG-INFO
InverseProblem.egg-info/SOURCES.txt
InverseProblem.egg-info/dependency_links.txt
InverseProblem.egg-info/not-zip-safe
InverseProblem.egg-info/top_level.txt