Metadata-Version: 1.0
Name: InverseProblem
Version: 1.0
Summary: Iterative Approach to using Tikhonov Regularizaiton for inverting a matrix
Home-page: http://github.com/kathrynthegreat/InverseProblem
Author: Kathryn The Great
Author-email: knv4@columbia.edu
License: Vasilaky
Platform: UNKNOWN
